foxglove_schemas_protobuf/ArrowPrimitive_pb2.py
foxglove_schemas_protobuf/ArrowPrimitive_pb2.pyi
foxglove_schemas_protobuf/CameraCalibration_pb2.py
foxglove_schemas_protobuf/CameraCalibration_pb2.pyi
foxglove_schemas_protobuf/CircleAnnotation_pb2.py
foxglove_schemas_protobuf/CircleAnnotation_pb2.pyi
foxglove_schemas_protobuf/Color_pb2.py
foxglove_schemas_protobuf/Color_pb2.pyi
foxglove_schemas_protobuf/CompressedImage_pb2.py
foxglove_schemas_protobuf/CompressedImage_pb2.pyi
foxglove_schemas_protobuf/CompressedVideo_pb2.py
foxglove_schemas_protobuf/CompressedVideo_pb2.pyi
foxglove_schemas_protobuf/CubePrimitive_pb2.py
foxglove_schemas_protobuf/CubePrimitive_pb2.pyi
foxglove_schemas_protobuf/CylinderPrimitive_pb2.py
foxglove_schemas_protobuf/CylinderPrimitive_pb2.pyi
foxglove_schemas_protobuf/FrameTransform_pb2.py
foxglove_schemas_protobuf/FrameTransform_pb2.pyi
foxglove_schemas_protobuf/FrameTransforms_pb2.py
foxglove_schemas_protobuf/FrameTransforms_pb2.pyi
foxglove_schemas_protobuf/GeoJSON_pb2.py
foxglove_schemas_protobuf/GeoJSON_pb2.pyi
foxglove_schemas_protobuf/Grid_pb2.py
foxglove_schemas_protobuf/Grid_pb2.pyi
foxglove_schemas_protobuf/ImageAnnotations_pb2.py
foxglove_schemas_protobuf/ImageAnnotations_pb2.pyi
foxglove_schemas_protobuf/KeyValuePair_pb2.py
foxglove_schemas_protobuf/KeyValuePair_pb2.pyi
foxglove_schemas_protobuf/LaserScan_pb2.py
foxglove_schemas_protobuf/LaserScan_pb2.pyi
foxglove_schemas_protobuf/LinePrimitive_pb2.py
foxglove_schemas_protobuf/LinePrimitive_pb2.pyi
foxglove_schemas_protobuf/LocationFix_pb2.py
foxglove_schemas_protobuf/LocationFix_pb2.pyi
foxglove_schemas_protobuf/Log_pb2.py
foxglove_schemas_protobuf/Log_pb2.pyi
foxglove_schemas_protobuf/ModelPrimitive_pb2.py
foxglove_schemas_protobuf/ModelPrimitive_pb2.pyi
foxglove_schemas_protobuf/PackedElementField_pb2.py
foxglove_schemas_protobuf/PackedElementField_pb2.pyi
foxglove_schemas_protobuf/Point2_pb2.py
foxglove_schemas_protobuf/Point2_pb2.pyi
foxglove_schemas_protobuf/Point3_pb2.py
foxglove_schemas_protobuf-0.3.0.dist-info/METADATA
foxglove_schemas_protobuf-0.3.0.dist-info/WHEEL
foxglove_schemas_protobuf-0.3.0.dist-info/RECORD
